Solarflare/conversions.py
Solarflare/nightcalc.py
Solarflare/solarflare.py
Solarflare-0.0.6.dist-info/METADATA
Solarflare-0.0.6.dist-info/WHEEL
Solarflare-0.0.6.dist-info/top_level.txt
Solarflare-0.0.6.dist-info/RECORD
