Metadata-Version: 2.1
Name: Solarflare
Version: 0.0.6
Summary: A Python library that deals with solar calculations
Home-page: https://github.com/PyndyalaCoder/Solarflare
Author: Siddhu Pendyala
Author-email: elcientifico.pendyala@gmail.com
License: MIT
Project-URL: Bug Tracker, https://github.com/PyndyalaCoder/Solarflare/issues
